madera/__init__.py
madera/globals.py
madera/util.py
madera/consumer/__init__.py
madera/consumer/topic_listener.py
madera/consumer/topic_watcher.py
madera/kafka/__init__.py
madera/kafka/kafka_2.12-2.3.0.tgz
madera/logging/__init__.py
madera/logging/frame.py
madera/logging/handler.py
madera/logging/publisher.py
madera/logging/uploader.py
madera/scripts/__init__.py
madera/scripts/maderad.py
madera/scripts/test_producer.py
madera/scripts/templates/__init__.py
madera/scripts/templates/kafka-server-start.sh.jinja
madera/scripts/templates/kafka_server_jaas.jinja
madera/scripts/templates/server.jinja
madera/scripts/templates/zookeeper.jinja
madera-1.0.2.dist-info/METADATA
madera-1.0.2.dist-info/RECORD
madera-1.0.2.dist-info/WHEEL
madera-1.0.2.dist-info/entry_points.txt
madera-1.0.2.dist-info/top_level.txt
